tws/__init__.py
tws/_async/__init__.py
tws/_async/client.py
tws/_sync/__init__.py
tws/_sync/client.py
tws/base/__init__.py
tws/base/client.py
tws/utils.py
tws_sdk-0.4.0.dist-info/LICENSE
tws_sdk-0.4.0.dist-info/METADATA
tws_sdk-0.4.0.dist-info/WHEEL
tws_sdk-0.4.0.dist-info/RECORD
