Metadata-Version: 2.1
Name: tws-sdk
Version: 0.4.0
Summary: TWS client for Python.
Home-page: https://github.com/Fireline-Science/tws-py
License: MIT
Author: Fireline Science
Author-email: sean@firelinescience.com
Requires-Python: >=3.9,<4.0
Classifier: License :: OSI Approved :: MIT License
Classifier: Operating System :: OS Independent
Classifier: Programming Language :: Python :: 3
Classifier: Programming Language :: Python :: 3.9
Classifier: Programming Language :: Python :: 3.10
Classifier: Programming Language :: Python :: 3.11
Classifier: Programming Language :: Python :: 3.12
Classifier: Programming Language :: Python :: 3.13
Requires-Dist: aiofiles (>=24.1.0,<25.0.0)
Requires-Dist: httpx[http2] (>=0.26,<0.29)
Project-URL: Documentation, https://github.com/Fireline-Science/tws-py
Project-URL: Repository, https://github.com/Fireline-Science/tws-py
